{
  "variants": {
    "facing=east,type=bottom": {
      "model": "mugann:block/grimoire_tome_vertical_bottom",
      "x": 270
    },
    "facing=east,type=double": {
      "model": "mugann:block/grimoire_tome_vertical_full",
      "x": 270
    },
    "facing=east,type=top": {
      "model": "mugann:block/grimoire_tome_vertical_top",
      "x": 270
    },
    "facing=north,type=bottom": {
      "model": "mugann:block/grimoire_tome_vertical_bottom",
      "x": 270,
      "y": 270
    },
    "facing=north,type=double": {
      "model": "mugann:block/grimoire_tome_vertical_full",
      "x": 270,
      "y": 270
    },
    "facing=north,type=top": {
      "model": "mugann:block/grimoire_tome_vertical_top",
      "x": 270,
      "y": 270
    },
    "facing=south,type=bottom": {
      "model": "mugann:block/grimoire_tome_vertical_bottom",
      "x": 90,
      "y": 90
    },
    "facing=south,type=double": {
      "model": "mugann:block/grimoire_tome_vertical_full",
      "x": 90,
      "y": 90
    },
    "facing=south,type=top": {
      "model": "mugann:block/grimoire_tome_vertical_top",
      "x": 90,
      "y": 90
    },
    "facing=west,type=bottom": {
      "model": "mugann:block/grimoire_tome_vertical_bottom",
      "x": 90,
      "y": 180
    },
    "facing=west,type=double": {
      "model": "mugann:block/grimoire_tome_vertical_full",
      "x": 90,
      "y": 180
    },
    "facing=west,type=top": {
      "model": "mugann:block/grimoire_tome_vertical_top",
      "x": 90,
      "y": 180
    }
  }
}